eetc_data_client/__init__.py
eetc_data_client/client.py
eetc_data_client-2.3.0.dist-info/licenses/LICENSE
eetc_data_client-2.3.0.dist-info/METADATA
eetc_data_client-2.3.0.dist-info/WHEEL
eetc_data_client-2.3.0.dist-info/top_level.txt
eetc_data_client-2.3.0.dist-info/RECORD
