Metadata-Version: 2.4
Name: eetc_data_client
Version: 2.3.0
Summary: EETC Data Hub Client Library
Author-email: East Empire Trading Company <eastempiretradingcompany2019@gmail.com>, Stefan Delic <einfach.jung1@gmail.com>, Milos Dovedan <dovedanmilosh@gmail.com>
Maintainer-email: East Empire Trading Company <eastempiretradingcompany2019@gmail.com>, Stefan Delic <einfach.jung1@gmail.com>, Milos Dovedan <dovedanmilosh@gmail.com>
License: Copyright (c) 2018 The Python Packaging Authority
Project-URL: Homepage, https://github.com/east-empire-trading-company/eetc-data-client
Project-URL: Bug Tracker, https://github.com/east-empire-trading-company/eetc-data-client/issues
Classifier: Programming Language :: Python :: 3
Classifier: License :: OSI Approved :: MIT License
Classifier: Operating System :: OS Independent
Requires-Python: >=3.8
License-File: LICENSE
Dynamic: license-file
